wszst_yaz0/__init__.py
wszst_yaz0/_version.py
wszst_yaz0-1.2.0.post1.dist-info/LICENSE
wszst_yaz0-1.2.0.post1.dist-info/METADATA
wszst_yaz0-1.2.0.post1.dist-info/WHEEL
wszst_yaz0-1.2.0.post1.dist-info/top_level.txt
wszst_yaz0-1.2.0.post1.dist-info/RECORD
