Metadata-Version: 2.1
Name: wszst-yaz0
Version: 1.2.0.post1
Summary: Quick and dirty wrapper around wszst
Home-page: https://github.com/leoetlino/wszst_yaz0
Author: leoetlino
Author-email: leo@leolam.fr
License: UNKNOWN
Platform: UNKNOWN
Classifier: License :: OSI Approved :: GNU General Public License v2 or later (GPLv2+)
Classifier: Topic :: Software Development :: Libraries
Requires-Python: >=3.6
